<request name="Oper5064" version="1.0" enable="True">
  	<group>Prueba</group> 
	<data>
  		<datasource>TOP/CLIENTES</datasource> 
  		<query>SELECT JTS_OID FROM SALDOS WHERE C1734 = 'U' AND C1785 = 4 AND (select FECHAPROCESO FROM PARAMETROS) > C1627  AND C1604 != 0 </query> 
  		<table>SALDOS</table> 
  		<stateField>PROCESADO</stateField> 
  		<processingMark>0</processingMark> 
  		<key>JTS_OID</key> 
  	</data>
	<operation>
  		<name>Operacion 5064</name> 
  		<type>1</type> 
  		<number>5064</number> 
  	</operation>
	 <scheduler>
  		<startHour>0900</startHour> 
  		<endHour>2300</endHour> 
  		<pollingInterval>10000</pollingInterval> 
  		<weekendDays>1</weekendDays> 
  		<holidayDays>1</holidayDays> 
  	</scheduler>
  </request>