<?xml version="1.0" encoding="UTF-8" standalone="yes"?>
<map>
    <class>
        <class-name>topsystems.topaz.server.objectsdomain.PlanDePagosOriginalChaco</class-name>
        <entity-name>topsystems.vo.PlanDePagosOriginal</entity-name>
        <table-name>PLANPAGOS_ORIGINAL</table-name>
        <database-name>TOP/CLIENTES</database-name>
        <attribute>
            <attribute-name>tz_lock</attribute-name>
            <column-name>TZ_LOCK</column-name>
        </attribute>
        <attribute>
            <attribute-name>SALDO_JTS_OID</attribute-name>
            <column-name>SALDO_JTS_OID</column-name>
            <key>primary</key>
        </attribute>
        <attribute>
            <attribute-name>CUO_NRO_CUOTA</attribute-name>
            <column-name>NUMERO_CUOTA</column-name>
            <key>primary</key>
        </attribute>
        <attribute>
            <attribute-name>CUO_FECHA_INICIO_CUOTA</attribute-name>
            <column-name>FECHA_INICIO</column-name>
        </attribute>
        <attribute>
            <attribute-name>CUO_FECHA_FIN_CUOTA</attribute-name>
            <column-name>FECHA_FIN</column-name>
        </attribute>
        <attribute>
            <attribute-name>CUO_TIPO_CUOTA</attribute-name>
            <column-name>TIPO_CUOTA</column-name>
        </attribute>
        <attribute>
            <attribute-name>CUO_CAPITAL_CUOTA</attribute-name>
            <column-name>CAPITAL</column-name>
        </attribute>
        <attribute>
            <attribute-name>CUO_INTERES_CUOTA</attribute-name>
            <column-name>INTERES</column-name>
        </attribute>
        <attribute>
            <attribute-name>CUO_REMANENTE_CAPITAL_CUOTA</attribute-name>
            <column-name>REMANENTE_CAPITAL</column-name>
        </attribute>
        <attribute>
            <attribute-name>CUO_IVA_INTERES</attribute-name>
            <column-name>IVAINTERES</column-name>
        </attribute>
        <attribute>
            <attribute-name>CUO_IVA_PERCEPCION_INTERES</attribute-name>
            <column-name>IVAPERCEPCIONINTERES</column-name>
        </attribute>
    </class>
</map>
